{
  "displayColumn": "name",
  "filterBuilder": "{\"condition\":\"AND\",\"rules\":[{\"key\":\"name\",\"operator\":\"contains\",\"value\":null,\"name\":\"Direction\",\"hidden\":false},{\"key\":\"pitch\",\"operator\":\"=\",\"value\":null,\"name\":\"Pitch\",\"hidden\":false}]}",
  "isReactive": true,
  "meta": {
    "applicationStatus": {
      "displayName": "Application Status",
      "invisible": false,
      "lookUpTable": "applicationStatus",
      "order": "1",
      "type": "lookup"
    },
    "applicationSubmit": {
      "displayName": "",
      "invisible": true,
      "order": "2",
      "startTitle": "Submit",
      "type": "workflow",
      "workflow": "-MS7l5yVEXqVer2WbOdY"
    },
    "approved": {
      "displayName": "Approved",
      "invisible": false,
      "order": "25",
      "type": "custom"
    },
    "createdBy": {
      "displayName": "Created By",
      "invisible": false,
      "order": "10",
      "type": "user"
    },
    "createdDate": {
      "displayName": "Created Date",
      "invisible": false,
      "order": "8",
      "type": "date"
    },
    "investor": {
      "displayName": "Investor",
      "invisible": false,
      "lookUpTable": "investorProfiles",
      "order": "3",
      "type": "lookup"
    },
    "investorCard": {
      "displayName": "Investor Card",
      "invisible": true,
      "order": "20",
      "type": "custom"
    },
    "isComplete": {
      "displayName": "isComplete",
      "invisible": false,
      "order": "11",
      "type": "checkbox"
    },
    "lastEditDate": {
      "displayName": "Last edit date",
      "invisible": false,
      "order": "9",
      "type": "date"
    },
    "lastEditedBy": {
      "displayName": "Last edited by",
      "invisible": true,
      "order": "16",
      "type": "user"
    },
    "mentor": {
      "displayName": "Mentor",
      "invisible": false,
      "lookUpTable": "mentors",
      "order": "5",
      "type": "lookup"
    },
    "mentorCard": {
      "displayName": "Mentor Card",
      "invisible": true,
      "order": "22",
      "type": "custom"
    },
    "messageDisplay": {
      "displayName": "Message",
      "invisible": false,
      "order": "21",
      "type": "custom"
    },
    "name": {
      "displayName": "Direction",
      "invisible": false,
      "order": "0",
      "type": "string"
    },
    "nextEvents": {
      "displayName": "Next Events",
      "invisible": false,
      "order": "13",
      "type": "string"
    },
    "notificationDescription": {
      "displayName": "Notification Description",
      "invisible": false,
      "order": "7",
      "type": "string"
    },
    "owner": {
      "displayName": "Owner",
      "invisible": false,
      "order": "12",
      "type": "user"
    },
    "pitch": {
      "displayName": "Pitch",
      "filterCode": "return row.sME == rowData.sME",
      "invisible": false,
      "lookUpTable": "slingshotPitches",
      "order": "4",
      "type": "lookup"
    },
    "pitchCard": {
      "displayName": "Company Card",
      "invisible": true,
      "order": "19",
      "type": "custom"
    },
    "referralTypeMentor": {
      "displayName": "Referral Type",
      "invisible": false,
      "lookUpTable": "referralType",
      "order": "17",
      "type": "lookup"
    },
    "referralTypeSME": {
      "displayName": "Referral Type",
      "invisible": false,
      "lookUpTable": "referralTypeSME",
      "order": "18",
      "type": "lookup"
    },
    "rejected": {
      "displayName": "Rejected",
      "invisible": false,
      "order": "26",
      "type": "custom"
    },
    "responseOpened": {
      "displayName": "responseOpened",
      "invisible": false,
      "order": "24",
      "type": "checkbox"
    },
    "sME": {
      "displayName": "SME",
      "invisible": false,
      "lookUpTable": "sMEProfiles",
      "order": "6",
      "type": "lookup"
    },
    "sMECard": {
      "displayName": "SME Card",
      "invisible": true,
      "order": "23",
      "type": "custom"
    },
    "sentMessage": {
      "displayName": "Sent Message",
      "invisible": true,
      "order": "15",
      "type": "custom"
    },
    "state": {
      "displayName": "State",
      "invisible": false,
      "order": "14",
      "type": "string"
    }
  },
  "rowEditorFieldsForm": {
    "sections": [
      {
        "name": "section_452705",
        "label": "Application",
        "clientKey": "section_452705",
        "order": 0,
        "rows": [
          {
            "name": "section_452705_row_827806",
            "label": "",
            "order": 0,
            "controls": [
              {
                "type": "custom",
                "name": "control_custom_644950",
                "fieldName": "control_custom_644950",
                "label": "Mentor Card",
                "order": 0,
                "defaultValue": "",
                "value": "",
                "className": "col-md-6",
                "readonly": false,
                "readonlyCondition": "",
                "placeholder": "",
                "labelBold": false,
                "labelItalic": false,
                "labelUnderline": false,
                "required": false,
                "requiredCondition": "",
                "isMultiLine": false,
                "isInteger": false,
                "decimalPlace": 0,
                "isTodayValue": false,
                "isTodayValueCreated": true,
                "dateFormat": "mm/dd/yy hh:mm p",
                "isCurrentUser": false,
                "isCurrentUserOwner": true,
                "isNowTimeValue": false,
                "timeFormat": "HH:mm",
                "isMultiple": false,
                "isAjax": false,
                "dataOptions": [],
                "ajaxDataUrl": "",
                "isChecked": false,
                "vif": "",
                "customCode": "<center>\r\n<b-card>\r\n<div class=\"card-body\" style=\"max-width: 100%;\">\r\n  <div class=\"row\">\r\n\r\n\r\n  </div>\r\n  <center><img :src=\"$getDashboardModel('mentors')[rowData.mentor].$profileImage$display\" style=\"border-radius: 15px; max-width:100px  \" /> </center>\r\n  <a href=\"#!\">\r\n  </a>\r\n  <div class=\"pt-4 text-center\">\r\n    <h5 class=\"h3 title\">\r\n      <span style=\"\" class=\"d-block mb-1\">{{rowData.$mentor.name}} {{rowData.$mentor.secondName}}</span>\r\n</h5>\r\n      <p class=\"h4 font-weight-light text-muted\"> {{truncateText(rowData.$mentor.aboutMe, 100)}} </p>\r\n\r\n\r\n        <p class=\"h4 font-weight-bold\" style=\"font-family: 'Grenette pro', sans-serif; font-size: 17px;     font-weight: 400;\"> Main Sectors: </p>\r\n          <p class=\"h4 font-weight-light\" v-for=\"item in rowData.$mentor.$mainSectors$display\">\r\n          <span style=\"font-family: 'Grenette pro', sans-serif; color: #ef4437 !important; font-size: 1em;     font-weight: 400;\">\r\n            <div class=\"rectangle\" style=\"padding: 2px; border-radius: 6px;\">\r\n              {{item}}\r\n            </div>\r\n          </span>\r\n        </p>\r\n      \r\n        <p class=\"h4 font-weight-bold\" style=\"font-family: 'Grenette pro', sans-serif; color: black; font-size: 17px;\"> Main Skills: </p>\r\n          <p class=\"h4 font-weight-light\" v-for=\"item in rowData.$mentor.$mainSkills$display\">\r\n          <span style=\"font-family: 'Grenette pro', sans-serif; color: #ef4437 !important; font-size: 1em;     font-weight: 400;\">\r\n            <div class=\"rectangle\" style=\"padding: 2px; border-radius: 6px;\">\r\n              {{item}}\r\n            </div>\r\n          </span>\r\n        </p>\r\n\r\n  \r\n    <div class=\"row justify-content-center\">\r\n   <a :href=\"rowData.$mentor.linkedInProfileLink\" target=\"_blank\">\r\n      <div v-if=\"rowData.$mentor.linkedInProfileLink\" class=\"social-icon-contain\">\r\n        <i v-if=\"rowData.$mentor.linkedInProfileLink\" style=\"padding: 5px; bottom: 0; color: white !important;\" class=\"fab fa-linkedin\"></i>\r\n      </div>\r\n      </a>\r\n    </div>\r\n    \r\n  </div>\r\n</div>\r\n</b-card>\r\n</center>",
                "invisible": true,
                "invisibleCondition": "$getUser('accountType') == 'Mentor' || $getUser('accountType') == 'Investor' || (rowData.name == 'Investor->SME' && $getUser('accountType') == 'SME')",
                "invisibleInDataGrid": true,
                "invisibleLabel": false,
                "enableCustomValidation": false,
                "customValidationRule": "",
                "customValidationErrorMessage": "",
                "propName": "mentorCard",
                "gridId": "applications"
              },
              {
                "type": "custom",
                "name": "control_custom_123914",
                "fieldName": "control_custom_123914",
                "label": "Company Card",
                "order": 1,
                "defaultValue": "",
                "value": "",
                "className": "col-md-6",
                "readonly": false,
                "readonlyCondition": "",
                "placeholder": "",
                "labelBold": false,
                "labelItalic": false,
                "labelUnderline": false,
                "required": false,
                "requiredCondition": "",
                "isMultiLine": false,
                "isInteger": false,
                "decimalPlace": 0,
                "isTodayValue": false,
                "isTodayValueCreated": true,
                "dateFormat": "mm/dd/yy hh:mm p",
                "isCurrentUser": false,
                "isCurrentUserOwner": true,
                "isNowTimeValue": false,
                "timeFormat": "HH:mm",
                "isMultiple": false,
                "isAjax": false,
                "dataOptions": [],
                "ajaxDataUrl": "",
                "isChecked": false,
                "vif": "",
                "customCode": "<center>\r\n  <b-card>\r\n<div class=\"card-body\" style=\"max-width: 100%;\">\r\n  <div class=\"row\">\r\n\r\n\r\n  </div>\r\n  <center><img :src=\"$getDashboardModel('slingshotPitches')[rowData.pitch].$companyLogo$display\" style=\"border-radius: 15px; max-width:100px  \" /> </center>\r\n  <a href=\"#!\">\r\n  </a>\r\n  <div class=\"pt-4 text-center\">\r\n    <h5 class=\"h3 title\">\r\n      <span style=\"\" class=\"d-block mb-1\">{{rowData.$pitch.name}}</span>\r\n</h5>\r\n      <p class=\"h4 font-weight-light text-muted\"> {{truncateText(rowData.$pitch.aboutTheCompany, 200)}} </p>\r\n\r\n       <div class=\"row justify-content-center\">\r\n      <div style=\"padding: 5px;\" v-if=\"rowData.$pitch.website\">\r\n        <a :href=\"'https://'+rowData.$pitch.website\" target=\"_blank\">\r\n          <div class=\"social-icon-contain\">\r\n          <i style=\"padding: 5px; color: white !important;\" class=\"fas fa-globe\"></i>\r\n          </div>\r\n        </a>\r\n      </div>\r\n\r\n      <div style=\"padding: 5px;\" v-if=\"rowData.$pitch.linkedInLink\">\r\n        <a :href=\"rowData.$pitch.linkedInLink\" target=\"_blank\">\r\n          <div class=\"social-icon-contain\">\r\n          <i style=\"padding: 5px; color: white !important;\" class=\"fab fa-linkedin\"></i>\r\n          </div>\r\n        </a>\r\n      </div>\r\n    </div>\r\n    \r\n  </div>\r\n</div>\r\n</b-card>\r\n</center>",
                "invisible": true,
                "invisibleCondition": "(rowData.name == 'SME->Mentor' && $getUser('accountType') == 'SME')",
                "invisibleInDataGrid": true,
                "invisibleLabel": false,
                "enableCustomValidation": false,
                "customValidationRule": "",
                "customValidationErrorMessage": "",
                "propName": "pitchCard",
                "gridId": "applications"
              },
              {
                "type": "custom",
                "name": "control_custom_558266",
                "fieldName": "control_custom_558266",
                "label": "Investor Card",
                "order": 2,
                "defaultValue": "",
                "value": "",
                "className": "col-md-6",
                "readonly": false,
                "readonlyCondition": "",
                "placeholder": "",
                "labelBold": false,
                "labelItalic": false,
                "labelUnderline": false,
                "required": false,
                "requiredCondition": "",
                "isMultiLine": false,
                "isInteger": false,
                "decimalPlace": 0,
                "isTodayValue": false,
                "isTodayValueCreated": true,
                "dateFormat": "mm/dd/yy hh:mm p",
                "isCurrentUser": false,
                "isCurrentUserOwner": true,
                "isNowTimeValue": false,
                "timeFormat": "HH:mm",
                "isMultiple": false,
                "isAjax": false,
                "dataOptions": [],
                "ajaxDataUrl": "",
                "isChecked": false,
                "vif": "",
                "customCode": "<center>\r\n  <b-card>\r\n<div class=\"card-body\" style=\"max-width: 100%;\">\r\n  <div class=\"row\">\r\n\r\n  </div>\r\n  <center><img :src=\"$getDashboardModel('investorProfiles')[rowData.investor].$profileImage$display\" style=\"border-radius: 15px; max-width:100px  \" /> </center>\r\n  <a href=\"#!\">\r\n  </a>\r\n  <div class=\"pt-4 text-center\">\r\n    <h5 class=\"h3 title\">\r\n      <span class=\"d-block mb-1\">{{rowData.$investor.name}} {{rowData.$investor.secondName}} </span>\r\n      <small id=\"about\" class=\"h4 font-weight-light text-muted\"></small>\r\n      \r\n      <div class=\"row\" style=\"justify-content:center;\"> \r\n      <small class=\"h4 font-weight-light text-muted\">{{rowData.$investor.phoneNumber}}</small>\r\n      </div>\r\n\r\n<div class=\"row\" style=\"justify-content:center;\">\r\n      <small class=\"h4 font-weight-light text-muted\" v-for='e in rowData.$investor.$owner$display'>\r\n        <a href=\"`mailto:${e}`\">{{e}}</a>\r\n      </small>\r\n</div>\r\n\r\n </h5>\r\n\r\n       <div class=\"row justify-content-center\">\r\n\r\n      <a :href=\"rowData.$investor.linkedInProfileLink\" target=\"_blank\">\r\n        <div v-if=\"rowData.$investor.linkedInProfileLink\" class=\"social-icon-contain\">\r\n        <i v-if=\"rowData.$investor.linkedInProfileLink\" style=\"padding: 5px; color: white !important;\" class=\"fab fa-linkedin\"></i>\r\n        </div>\r\n     </a>\r\n       </div>\r\n   \r\n  </div>\r\n</div>\r\n</b-card>\r\n</center>",
                "invisible": true,
                "invisibleCondition": "$getUser('accountType') == 'Investor' || $getUser('accountType') == 'Mentor' || rowData.name == 'Mentor->SME'  || rowData.name == 'SME->Mentor'",
                "invisibleInDataGrid": true,
                "invisibleLabel": false,
                "enableCustomValidation": false,
                "customValidationRule": "",
                "customValidationErrorMessage": "",
                "propName": "investorCard",
                "gridId": "applications"
              },
              {
                "type": "custom",
                "name": "control_custom_681888",
                "fieldName": "control_custom_681888",
                "label": "SME Card",
                "order": 3,
                "defaultValue": "",
                "value": "",
                "className": "col-md-6",
                "readonly": false,
                "readonlyCondition": "",
                "placeholder": "",
                "labelBold": false,
                "labelItalic": false,
                "labelUnderline": false,
                "required": false,
                "requiredCondition": "",
                "isMultiLine": false,
                "isInteger": false,
                "decimalPlace": 0,
                "isTodayValue": false,
                "isTodayValueCreated": true,
                "dateFormat": "mm/dd/yy hh:mm p",
                "isCurrentUser": false,
                "isCurrentUserOwner": true,
                "isNowTimeValue": false,
                "timeFormat": "HH:mm",
                "isMultiple": false,
                "isAjax": false,
                "dataOptions": [],
                "ajaxDataUrl": "",
                "isChecked": false,
                "vif": "",
                "customCode": "<center>\r\n  <b-card>\r\n<div class=\"card-body\" style=\"max-width: 100%;\">\r\n  <div class=\"row\">\r\n\r\n  </div>\r\n  <center><img :src=\"$getDashboardModel('sMEProfiles')[rowData.sME].$profileImage$display\" style=\"border-radius: 15px; max-width:100px  \" /> </center>\r\n  <a href=\"#!\">\r\n  </a>\r\n  <div class=\"pt-4 text-center\">\r\n    <h5 class=\"h3 title\">\r\n      <span class=\"d-block mb-1\">{{rowData.$sME.name}} {{rowData.$sME.secondName}} </span>\r\n      <small id=\"about\" class=\"h4 font-weight-light text-muted\"></small>\r\n\r\n </h5>\r\n\r\n       <div class=\"row justify-content-center\">\r\n      <a :href=\"rowData.$sME.linkedInProfileLink\" target=\"_blank\">\r\n        <div v-if=\"rowData.$sME.linkedInProfileLink\" class=\"social-icon-contain\">\r\n        <i v-if=\"rowData.$sME.linkedInProfileLink\" style=\"padding: 5px; bottom: 0; color: white !important;\" class=\"fab fa-linkedin\"></i>\r\n        </div>\r\n      </a>\r\n       </div>\r\n   \r\n  </div>\r\n</div>\r\n</b-card>\r\n</center>",
                "invisible": true,
                "invisibleCondition": "(rowData.name == 'Investor->SME' && $getUser('accountType') == 'SME') || (rowData.name  == 'SME->Mentor' && $getUser('accountType') == 'SME') || (rowData.name  == 'Mentor->SME' && $getUser('accountType') == 'SME')",
                "invisibleInDataGrid": true,
                "invisibleLabel": false,
                "enableCustomValidation": false,
                "customValidationRule": "",
                "customValidationErrorMessage": "",
                "propName": "sMECard",
                "gridId": "applications"
              },
              {
                "type": "lookup",
                "name": "control_lookup_650003",
                "fieldName": "control_lookup_650003",
                "label": "Pitch",
                "order": 4,
                "defaultValue": "",
                "value": "",
                "className": "col-md-12",
                "readonly": true,
                "readonlyCondition": "rowData.name == 'Mentor->SME' || $getUser('accountType') == 'Mentor' || $getUser('accountType') == 'Investor' || (rowData.name == 'Investor->SME'  && $getUser('accountType') == 'SME')",
                "placeholder": "",
                "labelBold": false,
                "labelItalic": false,
                "labelUnderline": false,
                "required": false,
                "requiredCondition": "",
                "isMultiLine": false,
                "isInteger": false,
                "decimalPlace": 0,
                "isTodayValue": false,
                "isTodayValueCreated": true,
                "dateFormat": "mm/dd/yy hh:mm p",
                "isCurrentUser": false,
                "isCurrentUserOwner": true,
                "isNowTimeValue": false,
                "timeFormat": "HH:mm",
                "isMultiple": false,
                "isAjax": false,
                "dataOptions": [],
                "ajaxDataUrl": "",
                "isChecked": false,
                "vif": "",
                "customCode": "",
                "invisible": true,
                "invisibleCondition": "(rowData.name == 'Mentor->SME'  && $getUser('accountType') == 'SME')|| (rowData.name == 'Investor->SME' && $getUser('accountType') == 'Investor') || (rowData.name == 'Investor->SME' && $getUser('accountType') == 'SME') || (rowData.name == 'SME->Mentor' && $getUser('accountType') == 'Mentor')",
                "invisibleInDataGrid": false,
                "invisibleLabel": false,
                "enableCustomValidation": false,
                "customValidationRule": "",
                "customValidationErrorMessage": "",
                "propName": "pitch",
                "ableToAddLookUpVal": false,
                "gridId": "applications",
                "description": ""
              },
              {
                "type": "lookup",
                "name": "control_lookup_541364",
                "fieldName": "control_lookup_541364",
                "label": "Referral Type",
                "order": 5,
                "defaultValue": "",
                "value": "",
                "className": "col-md-12",
                "readonly": true,
                "readonlyCondition": "(rowData.name == 'Mentor->SME' && $getUser('accountType') == 'SME' || (rowData.name == 'Investor->SME' && $getUser('accountType') == 'SME')) || ($getUser('accountType') == \"Mentor\" && rowData.$applicationStatus$display == \"Pending\") ",
                "placeholder": "",
                "labelBold": false,
                "labelItalic": false,
                "labelUnderline": false,
                "required": false,
                "requiredCondition": "$getUser('accountType') == 'Mentor' && $getUser('accountType') == 'Investor'",
                "isMultiLine": false,
                "isInteger": false,
                "decimalPlace": 0,
                "isTodayValue": false,
                "isTodayValueCreated": true,
                "dateFormat": "mm/dd/yy hh:mm p",
                "isCurrentUser": false,
                "isCurrentUserOwner": true,
                "isNowTimeValue": false,
                "timeFormat": "HH:mm",
                "isMultiple": false,
                "isAjax": false,
                "dataOptions": [],
                "ajaxDataUrl": "",
                "isChecked": false,
                "vif": "",
                "customCode": "",
                "invisible": true,
                "invisibleCondition": "rowData.name == 'SME->Mentor'",
                "invisibleInDataGrid": false,
                "invisibleLabel": false,
                "enableCustomValidation": false,
                "customValidationRule": "",
                "customValidationErrorMessage": "",
                "propName": "referralTypeSME",
                "ableToAddLookUpVal": false,
                "gridId": "applications"
              },
              {
                "type": "lookup",
                "name": "control_lookup_288783",
                "fieldName": "control_lookup_288783",
                "label": "Referral Type",
                "order": 6,
                "defaultValue": "",
                "value": "",
                "className": "col-md-12",
                "readonly": true,
                "readonlyCondition": "$getUser('accountType') == 'Mentor'",
                "placeholder": "",
                "labelBold": false,
                "labelItalic": false,
                "labelUnderline": false,
                "required": false,
                "requiredCondition": "",
                "isMultiLine": false,
                "isInteger": false,
                "decimalPlace": 0,
                "isTodayValue": false,
                "isTodayValueCreated": true,
                "dateFormat": "mm/dd/yy hh:mm p",
                "isCurrentUser": false,
                "isCurrentUserOwner": true,
                "isNowTimeValue": false,
                "timeFormat": "HH:mm",
                "isMultiple": false,
                "isAjax": false,
                "dataOptions": [],
                "ajaxDataUrl": "",
                "isChecked": false,
                "vif": "",
                "customCode": "",
                "invisible": true,
                "invisibleCondition": "rowData.name != 'SME->Mentor'",
                "invisibleInDataGrid": false,
                "invisibleLabel": false,
                "enableCustomValidation": false,
                "customValidationRule": "",
                "customValidationErrorMessage": "",
                "propName": "referralTypeMentor",
                "ableToAddLookUpVal": false,
                "gridId": "applications"
              },
              {
                "type": "multiline_text",
                "name": "control_multiline_text_445267",
                "fieldName": "control_multiline_text_445267",
                "label": "Message",
                "order": 7,
                "defaultValue": "",
                "value": "",
                "className": "col-md-12",
                "readonly": false,
                "readonlyCondition": "$getUser('accountType') == 'Mentor' || ($getUser('accountType') == \"Mentor\" && rowData.$applicationStatus$display == \"Pending\") ",
                "placeholder": "Message, why...",
                "labelBold": false,
                "labelItalic": false,
                "labelUnderline": false,
                "required": false,
                "requiredCondition": "(rowData.name == 'Investor->SME' && $getUser('accountType') == 'SME')",
                "isMultiLine": false,
                "isInteger": false,
                "decimalPlace": 0,
                "isTodayValue": false,
                "isTodayValueCreated": true,
                "dateFormat": "mm/dd/yy hh:mm p",
                "isCurrentUser": false,
                "isCurrentUserOwner": true,
                "isNowTimeValue": false,
                "timeFormat": "HH:mm",
                "isMultiple": false,
                "isAjax": false,
                "dataOptions": [],
                "ajaxDataUrl": "",
                "isChecked": false,
                "vif": "",
                "customCode": "",
                "invisible": true,
                "invisibleCondition": "(rowData.name == 'Investor->SME' && $getUser('accountType') == 'SME') || (rowData.name == 'SME->Mentor' && $getUser('accountType') == 'Mentor') || (rowData.name == 'Mentor->SME' && $getUser('accountType') == 'SME')",
                "invisibleInDataGrid": true,
                "invisibleLabel": false,
                "enableCustomValidation": false,
                "customValidationRule": "",
                "customValidationErrorMessage": "",
                "propName": "message",
                "gridId": "applications",
                "description": ""
              },
              {
                "type": "custom",
                "name": "control_custom_62198",
                "fieldName": "control_custom_62198",
                "label": "Message",
                "order": 8,
                "defaultValue": "",
                "value": "",
                "className": "col-md-12",
                "readonly": false,
                "readonlyCondition": "",
                "placeholder": "",
                "labelBold": false,
                "labelItalic": false,
                "labelUnderline": false,
                "required": false,
                "requiredCondition": "",
                "isMultiLine": false,
                "isInteger": false,
                "decimalPlace": 0,
                "isTodayValue": false,
                "isTodayValueCreated": true,
                "dateFormat": "mm/dd/yy hh:mm p",
                "isCurrentUser": false,
                "isCurrentUserOwner": true,
                "isNowTimeValue": false,
                "timeFormat": "HH:mm",
                "isMultiple": false,
                "isAjax": false,
                "dataOptions": [],
                "ajaxDataUrl": "",
                "isChecked": false,
                "vif": "",
                "customCode": "<p>{{rowData.message}}</p>",
                "invisible": true,
                "invisibleCondition": "(rowData.name  == 'Investor->SME' && $getUser('accountType') == 'Investor') || (rowData.name  == 'SME->Mentor' && $getUser('accountType') == 'SME') || (rowData.name  == 'Mentor->SME' && $getUser('accountType') == 'Mentor')",
                "invisibleInDataGrid": false,
                "invisibleLabel": false,
                "enableCustomValidation": false,
                "customValidationRule": "",
                "customValidationErrorMessage": "",
                "propName": "messageDisplay",
                "gridId": "applications"
              },
              {
                "type": "workflow",
                "name": "control_workflow_433100",
                "fieldName": "control_workflow_433100",
                "label": "",
                "order": 9,
                "defaultValue": "",
                "value": "",
                "className": "col-md-12",
                "readonly": false,
                "readonlyCondition": "",
                "placeholder": "",
                "labelBold": false,
                "labelItalic": false,
                "labelUnderline": false,
                "required": false,
                "requiredCondition": "",
                "isMultiLine": false,
                "isInteger": false,
                "decimalPlace": 0,
                "isTodayValue": false,
                "isTodayValueCreated": true,
                "dateFormat": "mm/dd/yy hh:mm p",
                "isCurrentUser": false,
                "isCurrentUserOwner": true,
                "isNowTimeValue": false,
                "timeFormat": "HH:mm",
                "isMultiple": false,
                "isAjax": false,
                "dataOptions": [],
                "ajaxDataUrl": "",
                "isChecked": false,
                "vif": "",
                "customCode": "",
                "invisible": true,
                "invisibleCondition": "(rowData.nextEvents && rowData.owner != fbUser.uid) || rowData.isComplete == 'true'  || rowData.nextEvents == 'Ok' ",
                "invisibleInDataGrid": true,
                "invisibleLabel": false,
                "enableCustomValidation": false,
                "customValidationRule": "",
                "customValidationErrorMessage": "",
                "propName": "applicationSubmit",
                "gridId": "applications"
              },
              {
                "type": "custom",
                "name": "control_custom_941764",
                "fieldName": "control_custom_941764",
                "label": "Sent Message",
                "order": 10,
                "defaultValue": "",
                "value": "",
                "className": "col-md-12",
                "readonly": false,
                "readonlyCondition": "",
                "placeholder": "",
                "labelBold": false,
                "labelItalic": false,
                "labelUnderline": false,
                "required": false,
                "requiredCondition": "",
                "isMultiLine": false,
                "isInteger": false,
                "decimalPlace": 0,
                "isTodayValue": false,
                "isTodayValueCreated": true,
                "dateFormat": "mm/dd/yy hh:mm p",
                "isCurrentUser": false,
                "isCurrentUserOwner": true,
                "isNowTimeValue": false,
                "timeFormat": "HH:mm",
                "isMultiple": false,
                "isAjax": false,
                "dataOptions": [],
                "ajaxDataUrl": "",
                "isChecked": false,
                "vif": "",
                "customCode": "<h3 style=\"color:black;\">Thanks for submitting. Please close this window and wait for a response.</h3>",
                "invisible": true,
                "invisibleCondition": "!rowData.nextEvents || rowData.owner == fbUser.uid || ($getUser('accountType') == \"SME\" && rowData.$applicationStatus$display == \"Approved\") || ($getUser('accountType') == \"Mentor\" && rowData.$applicationStatus$display == \"Approved\") ",
                "invisibleInDataGrid": true,
                "invisibleLabel": true,
                "enableCustomValidation": false,
                "customValidationRule": "",
                "customValidationErrorMessage": "",
                "propName": "sentMessage",
                "gridId": "applications"
              },
              {
                "type": "custom",
                "name": "control_custom_707059",
                "fieldName": "control_custom_707059",
                "label": "Rejected",
                "order": 0,
                "defaultValue": "",
                "value": "",
                "className": "col-md-12",
                "readonly": false,
                "readonlyCondition": "",
                "placeholder": "",
                "labelBold": false,
                "labelItalic": false,
                "labelUnderline": false,
                "required": false,
                "requiredCondition": "",
                "isMultiLine": false,
                "isInteger": false,
                "decimalPlace": 0,
                "isTodayValue": false,
                "isTodayValueCreated": true,
                "dateFormat": "mm/dd/yy hh:mm p",
                "isCurrentUser": false,
                "isCurrentUserOwner": true,
                "isNowTimeValue": false,
                "timeFormat": "HH:mm",
                "isMultiple": false,
                "isAjax": false,
                "dataOptions": [],
                "ajaxDataUrl": "",
                "isChecked": false,
                "vif": "",
                "customCode": "<h3 style=\"color:black;\">Application rejected.</h3>",
                "invisible": true,
                "invisibleCondition": " rowData.$applicationStatus$display != \"Rejected\"",
                "invisibleInDataGrid": false,
                "invisibleLabel": true,
                "enableCustomValidation": false,
                "customValidationRule": "",
                "customValidationErrorMessage": "",
                "propName": "rejected",
                "gridId": "applications"
              },
              {
                "type": "custom",
                "name": "control_custom_96757",
                "fieldName": "control_custom_96757",
                "label": "Approved",
                "order": 11,
                "defaultValue": "",
                "value": "",
                "className": "col-md-12",
                "readonly": false,
                "readonlyCondition": "",
                "placeholder": "",
                "labelBold": false,
                "labelItalic": false,
                "labelUnderline": false,
                "required": false,
                "requiredCondition": "",
                "isMultiLine": false,
                "isInteger": false,
                "decimalPlace": 0,
                "isTodayValue": false,
                "isTodayValueCreated": true,
                "dateFormat": "mm/dd/yy hh:mm p",
                "isCurrentUser": false,
                "isCurrentUserOwner": true,
                "isNowTimeValue": false,
                "timeFormat": "HH:mm",
                "isMultiple": false,
                "isAjax": false,
                "dataOptions": [],
                "ajaxDataUrl": "",
                "isChecked": false,
                "vif": "",
                "customCode": "<h3 style=\"color:black;\">Application approved.</h3>",
                "invisible": true,
                "invisibleCondition": " rowData.$applicationStatus$display != \"Approved\"",
                "invisibleInDataGrid": false,
                "invisibleLabel": true,
                "enableCustomValidation": false,
                "customValidationRule": "",
                "customValidationErrorMessage": "",
                "propName": "approved",
                "gridId": "applications"
              }
            ]
          }
        ],
        "labelPosition": "top",
        "isDynamic": false,
        "minInstance": 1,
        "maxInstance": 0,
        "instances": []
      },
      {
        "name": "section_291387",
        "label": "Details",
        "clientKey": "section_291387",
        "order": 0,
        "rows": [
          {
            "name": "section_291387_row_37115",
            "label": "",
            "order": 0,
            "controls": [
              {
                "type": "lookup",
                "name": "control_lookup_284007",
                "fieldName": "control_lookup_284007",
                "label": "SME",
                "order": 0,
                "defaultValue": "",
                "value": "",
                "className": "col-md-12",
                "readonly": true,
                "readonlyCondition": "",
                "placeholder": "",
                "labelBold": false,
                "labelItalic": false,
                "labelUnderline": false,
                "required": false,
                "requiredCondition": "",
                "isMultiLine": false,
                "isInteger": false,
                "decimalPlace": 0,
                "isTodayValue": false,
                "isTodayValueCreated": true,
                "dateFormat": "mm/dd/yy hh:mm p",
                "isCurrentUser": false,
                "isCurrentUserOwner": true,
                "isNowTimeValue": false,
                "timeFormat": "HH:mm",
                "isMultiple": false,
                "isAjax": false,
                "dataOptions": [],
                "ajaxDataUrl": "",
                "isChecked": false,
                "vif": "",
                "customCode": "",
                "invisible": false,
                "invisibleCondition": "$getUser('accountType') == 'SME' || $getUser('accountType') == 'Investor' || (rowData.name == 'SME->Mentor' && $getUser('accountType') == 'Mentor') || (rowData.name == 'Mentor->SME' && $getUser('accountType') == 'Mentor')",
                "invisibleInDataGrid": false,
                "invisibleLabel": false,
                "enableCustomValidation": false,
                "customValidationRule": "",
                "customValidationErrorMessage": "",
                "propName": "sME",
                "ableToAddLookUpVal": false,
                "gridId": "applications"
              },
              {
                "type": "lookup",
                "name": "control_lookup_152748",
                "fieldName": "control_lookup_152748",
                "label": "Mentor",
                "order": 1,
                "defaultValue": "",
                "value": "",
                "className": "col-md-12",
                "readonly": true,
                "readonlyCondition": "",
                "placeholder": "",
                "labelBold": false,
                "labelItalic": false,
                "labelUnderline": false,
                "required": false,
                "requiredCondition": "",
                "isMultiLine": false,
                "isInteger": false,
                "decimalPlace": 0,
                "isTodayValue": false,
                "isTodayValueCreated": true,
                "dateFormat": "mm/dd/yy hh:mm p",
                "isCurrentUser": false,
                "isCurrentUserOwner": true,
                "isNowTimeValue": false,
                "timeFormat": "HH:mm",
                "isMultiple": false,
                "isAjax": false,
                "dataOptions": [],
                "ajaxDataUrl": "",
                "isChecked": false,
                "vif": "",
                "customCode": "",
                "invisible": true,
                "invisibleCondition": "$getUser('accountType') == 'SME' ||$getUser('accountType') == 'Mentor' || $getUser('accountType') == 'Investor'  || (rowData.name == 'Investor->SME' && $getUser('accountType') == 'SME')",
                "invisibleInDataGrid": false,
                "invisibleLabel": false,
                "enableCustomValidation": false,
                "customValidationRule": "",
                "customValidationErrorMessage": "",
                "propName": "mentor",
                "ableToAddLookUpVal": false,
                "gridId": "applications"
              },
              {
                "type": "checkbox",
                "name": "control_checkbox_730343",
                "fieldName": "control_checkbox_730343",
                "label": "responseOpened",
                "order": 2,
                "defaultValue": "",
                "value": "",
                "className": "col-md-6",
                "readonly": false,
                "readonlyCondition": "",
                "placeholder": "",
                "labelBold": false,
                "labelItalic": false,
                "labelUnderline": false,
                "required": false,
                "requiredCondition": "",
                "isMultiLine": false,
                "isInteger": false,
                "decimalPlace": 0,
                "isTodayValue": false,
                "isTodayValueCreated": true,
                "dateFormat": "mm/dd/yy hh:mm p",
                "isCurrentUser": false,
                "isCurrentUserOwner": true,
                "isNowTimeValue": false,
                "timeFormat": "HH:mm",
                "isMultiple": false,
                "isAjax": false,
                "dataOptions": [],
                "ajaxDataUrl": "",
                "isChecked": false,
                "vif": "",
                "customCode": "",
                "invisible": false,
                "invisibleCondition": "",
                "invisibleInDataGrid": false,
                "invisibleLabel": false,
                "enableCustomValidation": false,
                "customValidationRule": "",
                "customValidationErrorMessage": "",
                "propName": "responseOpened"
              },
              {
                "type": "checkbox",
                "name": "control_checkbox_628457",
                "fieldName": "control_checkbox_628457",
                "label": "isComplete",
                "order": 3,
                "defaultValue": "",
                "value": "",
                "className": "col-md-6",
                "readonly": false,
                "readonlyCondition": "",
                "placeholder": "",
                "labelBold": false,
                "labelItalic": false,
                "labelUnderline": false,
                "required": false,
                "requiredCondition": "",
                "isMultiLine": false,
                "isInteger": false,
                "decimalPlace": 0,
                "isTodayValue": false,
                "isTodayValueCreated": true,
                "dateFormat": "mm/dd/yy hh:mm p",
                "isCurrentUser": false,
                "isCurrentUserOwner": true,
                "isNowTimeValue": false,
                "timeFormat": "HH:mm",
                "isMultiple": false,
                "isAjax": false,
                "dataOptions": [],
                "ajaxDataUrl": "",
                "isChecked": false,
                "vif": "",
                "customCode": "",
                "invisible": false,
                "invisibleCondition": "",
                "invisibleInDataGrid": false,
                "invisibleLabel": false,
                "enableCustomValidation": false,
                "customValidationRule": "",
                "customValidationErrorMessage": "",
                "propName": "isComplete",
                "gridId": "applications"
              },
              {
                "type": "text",
                "name": "control_text_253033",
                "fieldName": "control_text_253033",
                "label": "Direction",
                "order": 4,
                "defaultValue": "",
                "value": "",
                "className": "col-md-12",
                "readonly": true,
                "readonlyCondition": "",
                "placeholder": "",
                "labelBold": false,
                "labelItalic": false,
                "labelUnderline": false,
                "required": false,
                "requiredCondition": "",
                "isMultiLine": false,
                "isInteger": false,
                "decimalPlace": 0,
                "isTodayValue": false,
                "isTodayValueCreated": true,
                "dateFormat": "mm/dd/yy hh:mm p",
                "isCurrentUser": false,
                "isCurrentUserOwner": true,
                "isNowTimeValue": false,
                "timeFormat": "HH:mm",
                "isMultiple": false,
                "isAjax": false,
                "dataOptions": [],
                "ajaxDataUrl": "",
                "isChecked": false,
                "vif": "",
                "customCode": "",
                "invisible": false,
                "invisibleCondition": "",
                "invisibleInDataGrid": false,
                "invisibleLabel": false,
                "enableCustomValidation": false,
                "customValidationRule": "",
                "customValidationErrorMessage": "",
                "propName": "name",
                "gridId": "applications"
              },
              {
                "type": "text",
                "name": "control_text_165539",
                "fieldName": "control_text_165539",
                "label": "Notification Description",
                "order": 5,
                "defaultValue": "",
                "value": "",
                "className": "col-md-12",
                "readonly": true,
                "readonlyCondition": "",
                "placeholder": "",
                "labelBold": false,
                "labelItalic": false,
                "labelUnderline": false,
                "required": false,
                "requiredCondition": "",
                "isMultiLine": false,
                "isInteger": false,
                "decimalPlace": 0,
                "isTodayValue": false,
                "isTodayValueCreated": true,
                "dateFormat": "mm/dd/yy hh:mm p",
                "isCurrentUser": false,
                "isCurrentUserOwner": true,
                "isNowTimeValue": false,
                "timeFormat": "HH:mm",
                "isMultiple": false,
                "isAjax": false,
                "dataOptions": [],
                "ajaxDataUrl": "",
                "isChecked": false,
                "vif": "",
                "customCode": "",
                "invisible": false,
                "invisibleCondition": "",
                "invisibleInDataGrid": false,
                "invisibleLabel": false,
                "enableCustomValidation": false,
                "customValidationRule": "",
                "customValidationErrorMessage": "",
                "propName": "notificationDescription",
                "gridId": "applications"
              },
              {
                "type": "datepicker",
                "name": "control_datepicker_525491",
                "fieldName": "control_datepicker_525491",
                "label": "Created Date",
                "order": 6,
                "defaultValue": "",
                "value": "",
                "className": "col-md-6",
                "readonly": false,
                "readonlyCondition": "",
                "placeholder": "",
                "labelBold": false,
                "labelItalic": false,
                "labelUnderline": false,
                "required": false,
                "requiredCondition": "",
                "isMultiLine": false,
                "isInteger": false,
                "decimalPlace": 0,
                "isTodayValue": true,
                "isTodayValueCreated": true,
                "dateFormat": "mm/dd/yy hh:mm p",
                "isCurrentUser": false,
                "isCurrentUserOwner": true,
                "isNowTimeValue": false,
                "timeFormat": "HH:mm",
                "isMultiple": false,
                "isAjax": false,
                "dataOptions": [],
                "ajaxDataUrl": "",
                "isChecked": false,
                "vif": "",
                "customCode": "",
                "invisible": true,
                "invisibleCondition": "",
                "invisibleInDataGrid": false,
                "invisibleLabel": false,
                "enableCustomValidation": false,
                "customValidationRule": "",
                "customValidationErrorMessage": "",
                "propName": "createdDate",
                "gridId": "applications"
              },
              {
                "type": "user",
                "name": "control_user_197567",
                "fieldName": "control_user_197567",
                "label": "Created By",
                "order": 7,
                "defaultValue": "",
                "value": "",
                "className": "col-md-6",
                "readonly": false,
                "readonlyCondition": "",
                "placeholder": "",
                "labelBold": false,
                "labelItalic": false,
                "labelUnderline": false,
                "required": false,
                "requiredCondition": "",
                "isMultiLine": false,
                "isInteger": false,
                "decimalPlace": 0,
                "isTodayValue": false,
                "isTodayValueCreated": true,
                "dateFormat": "mm/dd/yy hh:mm p",
                "isCurrentUser": true,
                "isCurrentUserOwner": true,
                "isNowTimeValue": false,
                "timeFormat": "HH:mm",
                "isMultiple": false,
                "isAjax": false,
                "dataOptions": [],
                "ajaxDataUrl": "",
                "isChecked": false,
                "vif": "",
                "customCode": "",
                "invisible": false,
                "invisibleCondition": "",
                "invisibleInDataGrid": false,
                "invisibleLabel": false,
                "enableCustomValidation": false,
                "customValidationRule": "",
                "customValidationErrorMessage": "",
                "propName": "createdBy",
                "gridId": "applications"
              },
              {
                "type": "lookup",
                "name": "control_lookup_879651",
                "fieldName": "control_lookup_879651",
                "label": "Investor",
                "order": 8,
                "defaultValue": "",
                "value": "",
                "className": "col-md-12",
                "readonly": true,
                "readonlyCondition": "",
                "placeholder": "",
                "labelBold": false,
                "labelItalic": false,
                "labelUnderline": false,
                "required": false,
                "requiredCondition": "",
                "isMultiLine": false,
                "isInteger": false,
                "decimalPlace": 0,
                "isTodayValue": false,
                "isTodayValueCreated": true,
                "dateFormat": "mm/dd/yy hh:mm p",
                "isCurrentUser": false,
                "isCurrentUserOwner": true,
                "isNowTimeValue": false,
                "timeFormat": "HH:mm",
                "isMultiple": false,
                "isAjax": false,
                "dataOptions": [],
                "ajaxDataUrl": "",
                "isChecked": false,
                "vif": "",
                "customCode": "",
                "invisible": false,
                "invisibleCondition": "",
                "invisibleInDataGrid": false,
                "invisibleLabel": false,
                "enableCustomValidation": false,
                "customValidationRule": "",
                "customValidationErrorMessage": "",
                "propName": "investor",
                "ableToAddLookUpVal": true,
                "gridId": "applications"
              },
              {
                "type": "lookup",
                "name": "control_lookup_992071",
                "fieldName": "control_lookup_992071",
                "label": "Application Status",
                "order": 9,
                "defaultValue": "",
                "value": "",
                "className": "col-md-12",
                "readonly": true,
                "readonlyCondition": "",
                "placeholder": "",
                "labelBold": false,
                "labelItalic": false,
                "labelUnderline": false,
                "required": false,
                "requiredCondition": "",
                "isMultiLine": false,
                "isInteger": false,
                "decimalPlace": 0,
                "isTodayValue": false,
                "isTodayValueCreated": true,
                "dateFormat": "mm/dd/yy hh:mm p",
                "isCurrentUser": false,
                "isCurrentUserOwner": true,
                "isNowTimeValue": false,
                "timeFormat": "HH:mm",
                "isMultiple": false,
                "isAjax": false,
                "dataOptions": [],
                "ajaxDataUrl": "",
                "isChecked": false,
                "vif": "",
                "customCode": "",
                "invisible": false,
                "invisibleCondition": "",
                "invisibleInDataGrid": false,
                "invisibleLabel": false,
                "enableCustomValidation": false,
                "customValidationRule": "",
                "customValidationErrorMessage": "",
                "propName": "applicationStatus",
                "ableToAddLookUpVal": true,
                "gridId": "applications"
              },
              {
                "type": "text",
                "name": "control_text_652007",
                "fieldName": "control_text_652007",
                "label": "State",
                "order": 10,
                "defaultValue": "",
                "value": "",
                "className": "col-md-6",
                "readonly": false,
                "readonlyCondition": "",
                "placeholder": "",
                "labelBold": false,
                "labelItalic": false,
                "labelUnderline": false,
                "required": false,
                "requiredCondition": "",
                "isMultiLine": false,
                "isInteger": false,
                "decimalPlace": 0,
                "isTodayValue": false,
                "isTodayValueCreated": true,
                "dateFormat": "mm/dd/yy hh:mm p",
                "isCurrentUser": false,
                "isCurrentUserOwner": true,
                "isNowTimeValue": false,
                "timeFormat": "HH:mm",
                "isMultiple": false,
                "isAjax": false,
                "dataOptions": [],
                "ajaxDataUrl": "",
                "isChecked": false,
                "vif": "",
                "customCode": "",
                "invisible": true,
                "invisibleCondition": "true",
                "invisibleInDataGrid": false,
                "invisibleLabel": false,
                "enableCustomValidation": false,
                "customValidationRule": "",
                "customValidationErrorMessage": "",
                "propName": "state",
                "gridId": "applications"
              },
              {
                "type": "text",
                "name": "control_text_5639",
                "fieldName": "control_text_5639",
                "label": "Next Events",
                "order": 11,
                "defaultValue": "",
                "value": "",
                "className": "col-md-6",
                "readonly": false,
                "readonlyCondition": "",
                "placeholder": "",
                "labelBold": false,
                "labelItalic": false,
                "labelUnderline": false,
                "required": false,
                "requiredCondition": "",
                "isMultiLine": false,
                "isInteger": false,
                "decimalPlace": 0,
                "isTodayValue": false,
                "isTodayValueCreated": true,
                "dateFormat": "mm/dd/yy hh:mm p",
                "isCurrentUser": false,
                "isCurrentUserOwner": true,
                "isNowTimeValue": false,
                "timeFormat": "HH:mm",
                "isMultiple": false,
                "isAjax": false,
                "dataOptions": [],
                "ajaxDataUrl": "",
                "isChecked": false,
                "vif": "",
                "customCode": "",
                "invisible": false,
                "invisibleCondition": "",
                "invisibleInDataGrid": false,
                "invisibleLabel": false,
                "enableCustomValidation": false,
                "customValidationRule": "",
                "customValidationErrorMessage": "",
                "propName": "nextEvents",
                "gridId": "applications"
              },
              {
                "type": "user",
                "name": "control_user_982137",
                "fieldName": "control_user_982137",
                "label": "Owner",
                "order": 12,
                "defaultValue": "",
                "value": "",
                "className": "col-md-6",
                "readonly": false,
                "readonlyCondition": "",
                "placeholder": "",
                "labelBold": false,
                "labelItalic": false,
                "labelUnderline": false,
                "required": false,
                "requiredCondition": "",
                "isMultiLine": false,
                "isInteger": false,
                "decimalPlace": 0,
                "isTodayValue": false,
                "isTodayValueCreated": true,
                "dateFormat": "mm/dd/yy hh:mm p",
                "isCurrentUser": false,
                "isCurrentUserOwner": true,
                "isNowTimeValue": false,
                "timeFormat": "HH:mm",
                "isMultiple": false,
                "isAjax": false,
                "dataOptions": [],
                "ajaxDataUrl": "",
                "isChecked": false,
                "vif": "",
                "customCode": "",
                "invisible": false,
                "invisibleCondition": "",
                "invisibleInDataGrid": false,
                "invisibleLabel": false,
                "enableCustomValidation": false,
                "customValidationRule": "",
                "customValidationErrorMessage": "",
                "propName": "owner",
                "gridId": "applications"
              },
              {
                "type": "text",
                "name": "control_text_612779",
                "fieldName": "control_text_612779",
                "label": "State",
                "order": 13,
                "defaultValue": "",
                "value": "",
                "className": "col-md-6",
                "readonly": false,
                "readonlyCondition": "",
                "placeholder": "",
                "labelBold": false,
                "labelItalic": false,
                "labelUnderline": false,
                "required": false,
                "requiredCondition": "",
                "isMultiLine": false,
                "isInteger": false,
                "decimalPlace": 0,
                "isTodayValue": false,
                "isTodayValueCreated": true,
                "dateFormat": "mm/dd/yy hh:mm p",
                "isCurrentUser": false,
                "isCurrentUserOwner": true,
                "isNowTimeValue": false,
                "timeFormat": "HH:mm",
                "isMultiple": false,
                "isAjax": false,
                "dataOptions": [],
                "ajaxDataUrl": "",
                "isChecked": false,
                "vif": "",
                "customCode": "",
                "invisible": false,
                "invisibleCondition": "",
                "invisibleInDataGrid": false,
                "invisibleLabel": false,
                "enableCustomValidation": false,
                "customValidationRule": "",
                "customValidationErrorMessage": "",
                "propName": "state",
                "gridId": "applications"
              },
              {
                "type": "user",
                "name": "control_user_328795",
                "fieldName": "control_user_328795",
                "label": "Last edited by",
                "order": 14,
                "defaultValue": "",
                "value": "",
                "className": "col-md-6",
                "readonly": true,
                "readonlyCondition": "",
                "placeholder": "",
                "labelBold": false,
                "labelItalic": false,
                "labelUnderline": false,
                "required": false,
                "requiredCondition": "",
                "isMultiLine": false,
                "isInteger": false,
                "decimalPlace": 0,
                "isTodayValue": false,
                "isTodayValueCreated": true,
                "dateFormat": "mm/dd/yy hh:mm p",
                "isCurrentUser": false,
                "isCurrentUserOwner": true,
                "isNowTimeValue": false,
                "timeFormat": "HH:mm",
                "isMultiple": false,
                "isAjax": false,
                "dataOptions": [],
                "ajaxDataUrl": "",
                "isChecked": false,
                "vif": "",
                "customCode": "",
                "invisible": true,
                "invisibleCondition": "",
                "invisibleInDataGrid": true,
                "invisibleLabel": false,
                "enableCustomValidation": false,
                "customValidationRule": "",
                "customValidationErrorMessage": "",
                "propName": "lastEditedBy",
                "gridId": "applications"
              },
              {
                "type": "text",
                "name": "control_text_946606",
                "fieldName": "control_text_946606",
                "label": "nextEvents",
                "order": 15,
                "defaultValue": "",
                "value": "",
                "className": "col-md-6",
                "readonly": false,
                "readonlyCondition": "",
                "placeholder": "",
                "labelBold": false,
                "labelItalic": false,
                "labelUnderline": false,
                "required": false,
                "requiredCondition": "",
                "isMultiLine": false,
                "isInteger": false,
                "decimalPlace": 0,
                "isTodayValue": false,
                "isTodayValueCreated": true,
                "dateFormat": "mm/dd/yy hh:mm p",
                "isCurrentUser": false,
                "isCurrentUserOwner": true,
                "isNowTimeValue": false,
                "timeFormat": "HH:mm",
                "isMultiple": false,
                "isAjax": false,
                "dataOptions": [],
                "ajaxDataUrl": "",
                "isChecked": false,
                "vif": "",
                "customCode": "",
                "invisible": true,
                "invisibleCondition": "true",
                "invisibleInDataGrid": false,
                "invisibleLabel": false,
                "enableCustomValidation": false,
                "customValidationRule": "",
                "customValidationErrorMessage": "",
                "propName": "nextEvents",
                "gridId": "applications"
              },
              {
                "type": "datepicker",
                "name": "control_datepicker_43939",
                "fieldName": "control_datepicker_43939",
                "label": "Last edit date",
                "order": 16,
                "defaultValue": "",
                "value": "",
                "className": "col-md-6",
                "readonly": true,
                "readonlyCondition": "",
                "placeholder": "",
                "labelBold": false,
                "labelItalic": false,
                "labelUnderline": false,
                "required": false,
                "requiredCondition": "",
                "isMultiLine": false,
                "isInteger": false,
                "decimalPlace": 0,
                "isTodayValue": false,
                "isTodayValueCreated": true,
                "dateFormat": "mm/dd/yy hh:mm p",
                "isCurrentUser": false,
                "isCurrentUserOwner": true,
                "isNowTimeValue": false,
                "timeFormat": "HH:mm",
                "isMultiple": false,
                "isAjax": false,
                "dataOptions": [],
                "ajaxDataUrl": "",
                "isChecked": false,
                "vif": "",
                "customCode": "",
                "invisible": true,
                "invisibleCondition": "",
                "invisibleInDataGrid": false,
                "invisibleLabel": false,
                "enableCustomValidation": false,
                "customValidationRule": "",
                "customValidationErrorMessage": "",
                "propName": "lastEditDate",
                "gridId": "applications"
              }
            ]
          }
        ],
        "labelPosition": "top",
        "isDynamic": false,
        "minInstance": 1,
        "maxInstance": 0,
        "instances": [],
        "vif": "$getUser('accountType') == \"Admin\""
      }
    ],
    "layout": "tab",
    "_uniqueId": 0.030152841898361205
  },
  "source": "applications",
  "storageType": "dashboard",
  "title": "Applications",
  "views": {
    "accountNotifications": {
      "filterBuilder": "{\"condition\":\"AND\",\"rules\":[{\"key\":\"owner\",\"operator\":\"=\",\"value\":\"fbUser.uid\",\"name\":\"Owner\",\"expression\":true,\"hidden\":true},{\"key\":\"applicationStatus\",\"operator\":\"!=\",\"value\":{\"value\":\"-MS2D3bgt4vWZpZco7Aw\",\"name\":\"Approved\"},\"name\":\"isApproved\",\"hidden\":true}]}",
      "meta": {
        "applicationStatus": {
          "invisible": false,
          "order": "1"
        },
        "applicationSubmit": {
          "invisible": false,
          "order": "2"
        },
        "approved": {
          "order": 25
        },
        "createdBy": {
          "order": "9"
        },
        "createdDate": {
          "invisible": false,
          "order": "7"
        },
        "investor": {
          "invisible": false,
          "order": "3"
        },
        "investorCard": {
          "order": 20
        },
        "isComplete": {
          "order": "10"
        },
        "lastEditDate": {
          "invisible": false,
          "order": "8"
        },
        "lastEditedBy": {
          "invisible": true,
          "order": "15"
        },
        "mentor": {
          "invisible": false,
          "order": "4"
        },
        "mentorCard": {
          "order": 22
        },
        "messageDisplay": {
          "order": 21
        },
        "name": {
          "invisible": false,
          "order": "0"
        },
        "nextEvents": {
          "order": "12"
        },
        "notificationDescription": {
          "order": "6"
        },
        "owner": {
          "invisible": false,
          "order": "11"
        },
        "pitch": {
          "invisible": false,
          "order": "16"
        },
        "pitchCard": {
          "order": 19
        },
        "referralTypeMentor": {
          "order": "17"
        },
        "referralTypeSME": {
          "order": "18"
        },
        "rejected": {
          "order": 26
        },
        "responseOpened": {
          "order": 24
        },
        "sME": {
          "invisible": false,
          "order": "5"
        },
        "sMECard": {
          "order": 23
        },
        "sentMessage": {
          "invisible": false,
          "order": "14"
        },
        "state": {
          "order": "13"
        }
      },
      "title": "Account Notifications",
      "viewTemplate": {
        "colsPerRow": 1,
        "maxWidth": "600",
        "type": "card-list"
      }
    },
    "mentorAndSessions": {
      "filterBuilder": "{\"condition\":\"AND\",\"rules\":[{\"key\":\"mentor\",\"operator\":\"=\",\"value\":\"$getUser('profileID')\",\"name\":\"Mentor\",\"expression\":true,\"hidden\":true},{\"key\":\"applicationStatus\",\"operator\":\"=\",\"value\":{\"value\":\"-MS2D3bgt4vWZpZco7Aw\",\"name\":\"Approved\"},\"name\":\"Approved\",\"hidden\":true},{\"key\":\"isComplete\",\"operator\":\"checkbox\",\"value\":true,\"name\":\"Complete\",\"hidden\":true},{\"key\":\"name\",\"operator\":\"!=\",\"value\":\"Investor->SME\",\"name\":\"Direction Not\",\"hidden\":true}]}",
      "meta": {
        "applicationStatus": {
          "invisible": false,
          "order": "1"
        },
        "applicationSubmit": {
          "invisible": true,
          "order": "4"
        },
        "approved": {
          "order": 25
        },
        "createdBy": {
          "invisible": false,
          "order": "2"
        },
        "createdDate": {
          "invisible": false,
          "order": "9"
        },
        "investor": {
          "invisible": false,
          "order": "5"
        },
        "investorCard": {
          "order": 20
        },
        "isComplete": {
          "invisible": false,
          "order": "3"
        },
        "lastEditDate": {
          "invisible": false,
          "order": "10"
        },
        "lastEditedBy": {
          "invisible": true,
          "order": "16"
        },
        "mentor": {
          "invisible": false,
          "order": "6"
        },
        "mentorCard": {
          "order": 22
        },
        "messageDisplay": {
          "order": 21
        },
        "name": {
          "invisible": false,
          "order": "0"
        },
        "nextEvents": {
          "invisible": false,
          "order": "12"
        },
        "notificationDescription": {
          "invisible": false,
          "order": "8"
        },
        "owner": {
          "invisible": false,
          "order": "11"
        },
        "pitch": {
          "invisible": false,
          "order": "14"
        },
        "pitchCard": {
          "order": 19
        },
        "referralTypeMentor": {
          "invisible": false,
          "order": "17"
        },
        "referralTypeSME": {
          "invisible": false,
          "order": "18"
        },
        "rejected": {
          "order": 26
        },
        "responseOpened": {
          "order": 24
        },
        "sME": {
          "invisible": false,
          "order": "7"
        },
        "sMECard": {
          "order": 23
        },
        "sentMessage": {
          "invisible": true,
          "order": "15"
        },
        "state": {
          "invisible": false,
          "order": "13"
        }
      },
      "title": "Mentor and Sessions"
    },
    "myMentors": {
      "filterBuilder": "{\"condition\":\"AND\",\"rules\":[{\"key\":\"sME\",\"operator\":\"=\",\"value\":\"$getUser('profileID')\",\"name\":\"SME\",\"expression\":true,\"hidden\":true},{\"key\":\"applicationStatus\",\"operator\":\"=\",\"value\":{\"value\":\"-MS2D3bgt4vWZpZco7Aw\",\"name\":\"Approved\"},\"name\":\"Approved\",\"hidden\":true},{\"key\":\"isComplete\",\"operator\":\"checkbox\",\"value\":true,\"name\":\"Complete\",\"hidden\":true},{\"key\":\"name\",\"operator\":\"!=\",\"value\":\"Investor->SME\",\"name\":\"Direction Not Investor\",\"hidden\":true}]}",
      "meta": {
        "applicationStatus": {
          "invisible": false,
          "order": "1"
        },
        "applicationSubmit": {
          "invisible": true,
          "order": "4"
        },
        "approved": {
          "order": 25
        },
        "createdBy": {
          "invisible": false,
          "order": "2"
        },
        "createdDate": {
          "invisible": false,
          "order": "9"
        },
        "investor": {
          "invisible": false,
          "order": "5"
        },
        "investorCard": {
          "order": 20
        },
        "isComplete": {
          "invisible": false,
          "order": "3"
        },
        "lastEditDate": {
          "invisible": false,
          "order": "10"
        },
        "lastEditedBy": {
          "invisible": true,
          "order": "16"
        },
        "mentor": {
          "invisible": false,
          "order": "6"
        },
        "mentorCard": {
          "order": 22
        },
        "messageDisplay": {
          "order": 21
        },
        "name": {
          "invisible": false,
          "order": "0"
        },
        "nextEvents": {
          "invisible": false,
          "order": "12"
        },
        "notificationDescription": {
          "invisible": false,
          "order": "8"
        },
        "owner": {
          "invisible": false,
          "order": "11"
        },
        "pitch": {
          "invisible": false,
          "order": "14"
        },
        "pitchCard": {
          "order": 19
        },
        "referralTypeMentor": {
          "invisible": false,
          "order": "17"
        },
        "referralTypeSME": {
          "invisible": false,
          "order": "18"
        },
        "rejected": {
          "order": 26
        },
        "responseOpened": {
          "order": 24
        },
        "sME": {
          "invisible": false,
          "order": "7"
        },
        "sMECard": {
          "order": 23
        },
        "sentMessage": {
          "invisible": true,
          "order": "15"
        },
        "state": {
          "invisible": false,
          "order": "13"
        }
      },
      "title": "My Mentors"
    }
  }
}