{
  "displayColumn": "name",
  "isReactive": true,
  "meta": {
    "createdDate": {
      "displayName": "Created Date",
      "invisible": true,
      "order": 3,
      "type": "date"
    },
    "lastEditDate": {
      "displayName": "Last edit date",
      "invisible": true,
      "order": 7,
      "type": "date"
    },
    "lastEditedBy": {
      "displayName": "Last edited by",
      "invisible": true,
      "order": 6,
      "type": "user"
    },
    "layout": {
      "displayName": "Layout",
      "order": 1,
      "type": "select"
    },
    "name": {
      "Width": "403px",
      "displayName": "Name",
      "order": 0,
      "type": "string"
    },
    "nextEvents": {
      "displayName": "Next Events",
      "invisible": true,
      "order": 5,
      "type": "string"
    },
    "owner": {
      "displayName": "Owner",
      "order": 2,
      "type": "user"
    },
    "state": {
      "displayName": "State",
      "invisible": true,
      "order": 4,
      "type": "string"
    }
  },
  "rowEditorFieldsForm": {
    "sections": [
      {
        "name": "section_149050",
        "label": "",
        "clientKey": "section_149050",
        "order": 0,
        "rows": [
          {
            "name": "section_149050_row_969028",
            "label": "",
            "order": 0,
            "controls": [
              {
                "type": "text",
                "name": "control_cf5592e0-2cd9-11ec-a2f7-879f75befbaf",
                "fieldName": "control_cf5592e0-2cd9-11ec-a2f7-879f75befbaf",
                "label": "Name",
                "order": 0,
                "defaultValue": "",
                "value": "",
                "className": "col-md-12",
                "readonly": true,
                "readonlyCondition": "",
                "placeholder": "",
                "required": false,
                "requiredCondition": "",
                "isMultiLine": false,
                "isInteger": false,
                "decimalPlace": 0,
                "isTodayValue": false,
                "isTodayValueCreated": true,
                "dateFormat": "mm/dd/yy hh:mm p",
                "isCurrentUser": false,
                "isCurrentUserOwner": true,
                "isNowTimeValue": false,
                "timeFormat": "HH:mm",
                "isMultiple": false,
                "isAjax": false,
                "dataOptions": [],
                "ajaxDataUrl": "",
                "isChecked": false,
                "vif": "",
                "customCode": "",
                "invisible": false,
                "invisibleCondition": "",
                "invisibleInDataGrid": false,
                "invisibleLabel": false,
                "enableCustomValidation": false,
                "customValidationRule": "",
                "customValidationErrorMessage": "",
                "mask": "",
                "lookupOpenInModalDisabled": false,
                "propName": "name",
                "gridId": "investorTypes"
              }
            ]
          }
        ],
        "labelPosition": "top",
        "isDynamic": false,
        "minInstance": 1,
        "maxInstance": 0,
        "instances": []
      },
      {
        "cleintKey": "hidden_section_cf556bd0-2cd9-11ec-a2f7-879f75befbaf",
        "instances": [],
        "isDynamic": false,
        "label": "Hidden Section",
        "vif": "false",
        "name": "hidden_section_cf556bd0-2cd9-11ec-a2f7-879f75befbaf",
        "order": 1,
        "rows": [
          {
            "name": "hidden_section_cf556bd0-2cd9-11ec-a2f7-879f75befbaf_row_cf556bd1-2cd9-11ec-a2f7-879f75befbaf",
            "controls": [
              {
                "type": "select",
                "name": "control_cf72dee0-2cd9-11ec-a2f7-879f75befbaf",
                "fieldName": "control_cf72dee0-2cd9-11ec-a2f7-879f75befbaf",
                "label": "Layout",
                "order": 0,
                "defaultValue": "",
                "value": "",
                "className": "col-md-6",
                "readonly": false,
                "readonlyCondition": "",
                "placeholder": "",
                "required": false,
                "requiredCondition": "",
                "isMultiLine": false,
                "isInteger": false,
                "decimalPlace": 0,
                "isTodayValue": false,
                "isTodayValueCreated": true,
                "dateFormat": "mm/dd/yy hh:mm p",
                "isCurrentUser": false,
                "isCurrentUserOwner": true,
                "isNowTimeValue": false,
                "timeFormat": "HH:mm",
                "isMultiple": false,
                "isAjax": false,
                "dataOptions": [],
                "ajaxDataUrl": "",
                "isChecked": false,
                "vif": "",
                "customCode": "",
                "invisible": false,
                "invisibleCondition": "",
                "invisibleInDataGrid": true,
                "invisibleLabel": false,
                "enableCustomValidation": false,
                "customValidationRule": "",
                "customValidationErrorMessage": "",
                "mask": "",
                "lookupOpenInModalDisabled": false,
                "propName": "layout",
                "gridId": "investorTypes"
              },
              {
                "type": "user",
                "name": "control_cf881490-2cd9-11ec-a2f7-879f75befbaf",
                "fieldName": "control_cf881490-2cd9-11ec-a2f7-879f75befbaf",
                "label": "Owner",
                "order": 0,
                "defaultValue": "",
                "value": "",
                "className": "col-md-6",
                "readonly": false,
                "readonlyCondition": "",
                "placeholder": "",
                "required": false,
                "requiredCondition": "",
                "isMultiLine": false,
                "isInteger": false,
                "decimalPlace": 0,
                "isTodayValue": false,
                "isTodayValueCreated": true,
                "dateFormat": "mm/dd/yy hh:mm p",
                "isCurrentUser": false,
                "isCurrentUserOwner": true,
                "isNowTimeValue": false,
                "timeFormat": "HH:mm",
                "isMultiple": false,
                "isAjax": false,
                "dataOptions": [],
                "ajaxDataUrl": "",
                "isChecked": false,
                "vif": "",
                "customCode": "",
                "invisible": false,
                "invisibleCondition": "",
                "invisibleInDataGrid": true,
                "invisibleLabel": false,
                "enableCustomValidation": false,
                "customValidationRule": "",
                "customValidationErrorMessage": "",
                "mask": "",
                "lookupOpenInModalDisabled": false,
                "propName": "owner",
                "gridId": "investorTypes"
              },
              {
                "type": "text",
                "name": "control_cfbd2e50-2cd9-11ec-a2f7-879f75befbaf",
                "fieldName": "control_cfbd2e50-2cd9-11ec-a2f7-879f75befbaf",
                "label": "State",
                "order": 0,
                "defaultValue": "",
                "value": "",
                "className": "col-md-6",
                "readonly": false,
                "readonlyCondition": "",
                "placeholder": "",
                "required": false,
                "requiredCondition": "",
                "isMultiLine": false,
                "isInteger": false,
                "decimalPlace": 0,
                "isTodayValue": false,
                "isTodayValueCreated": true,
                "dateFormat": "mm/dd/yy hh:mm p",
                "isCurrentUser": false,
                "isCurrentUserOwner": true,
                "isNowTimeValue": false,
                "timeFormat": "HH:mm",
                "isMultiple": false,
                "isAjax": false,
                "dataOptions": [],
                "ajaxDataUrl": "",
                "isChecked": false,
                "vif": "",
                "customCode": "",
                "invisible": true,
                "invisibleCondition": "",
                "invisibleInDataGrid": false,
                "invisibleLabel": false,
                "enableCustomValidation": false,
                "customValidationRule": "",
                "customValidationErrorMessage": "",
                "mask": "",
                "lookupOpenInModalDisabled": false,
                "propName": "state"
              },
              {
                "type": "datepicker",
                "name": "control_cfa0a5a0-2cd9-11ec-a2f7-879f75befbaf",
                "fieldName": "control_cfa0a5a0-2cd9-11ec-a2f7-879f75befbaf",
                "label": "Created Date",
                "order": 0,
                "defaultValue": "",
                "value": "",
                "className": "col-md-6",
                "readonly": false,
                "readonlyCondition": "",
                "placeholder": "",
                "required": false,
                "requiredCondition": "",
                "isMultiLine": false,
                "isInteger": false,
                "decimalPlace": 0,
                "isTodayValue": false,
                "isTodayValueCreated": true,
                "dateFormat": "mm/dd/yy hh:mm p",
                "isCurrentUser": false,
                "isCurrentUserOwner": true,
                "isNowTimeValue": false,
                "timeFormat": "HH:mm",
                "isMultiple": false,
                "isAjax": false,
                "dataOptions": [],
                "ajaxDataUrl": "",
                "isChecked": false,
                "vif": "",
                "customCode": "",
                "invisible": true,
                "invisibleCondition": "",
                "invisibleInDataGrid": false,
                "invisibleLabel": false,
                "enableCustomValidation": false,
                "customValidationRule": "",
                "customValidationErrorMessage": "",
                "mask": "",
                "lookupOpenInModalDisabled": false,
                "propName": "createdDate"
              },
              {
                "type": "text",
                "name": "control_cfd91ac0-2cd9-11ec-a2f7-879f75befbaf",
                "fieldName": "control_cfd91ac0-2cd9-11ec-a2f7-879f75befbaf",
                "label": "Next Events",
                "order": 0,
                "defaultValue": "",
                "value": "",
                "className": "col-md-6",
                "readonly": false,
                "readonlyCondition": "",
                "placeholder": "",
                "required": false,
                "requiredCondition": "",
                "isMultiLine": false,
                "isInteger": false,
                "decimalPlace": 0,
                "isTodayValue": false,
                "isTodayValueCreated": true,
                "dateFormat": "mm/dd/yy hh:mm p",
                "isCurrentUser": false,
                "isCurrentUserOwner": true,
                "isNowTimeValue": false,
                "timeFormat": "HH:mm",
                "isMultiple": false,
                "isAjax": false,
                "dataOptions": [],
                "ajaxDataUrl": "",
                "isChecked": false,
                "vif": "",
                "customCode": "",
                "invisible": true,
                "invisibleCondition": "",
                "invisibleInDataGrid": false,
                "invisibleLabel": false,
                "enableCustomValidation": false,
                "customValidationRule": "",
                "customValidationErrorMessage": "",
                "mask": "",
                "lookupOpenInModalDisabled": false,
                "propName": "nextEvents"
              },
              {
                "type": "user",
                "name": "control_cff57c60-2cd9-11ec-a2f7-879f75befbaf",
                "fieldName": "control_cff57c60-2cd9-11ec-a2f7-879f75befbaf",
                "label": "Last edited by",
                "order": 0,
                "defaultValue": "",
                "value": "",
                "className": "col-md-6",
                "readonly": true,
                "readonlyCondition": "",
                "placeholder": "",
                "required": false,
                "requiredCondition": "",
                "isMultiLine": false,
                "isInteger": false,
                "decimalPlace": 0,
                "isTodayValue": false,
                "isTodayValueCreated": true,
                "dateFormat": "mm/dd/yy hh:mm p",
                "isCurrentUser": false,
                "isCurrentUserOwner": true,
                "isNowTimeValue": false,
                "timeFormat": "HH:mm",
                "isMultiple": false,
                "isAjax": false,
                "dataOptions": [],
                "ajaxDataUrl": "",
                "isChecked": false,
                "vif": "",
                "customCode": "",
                "invisible": true,
                "invisibleCondition": "",
                "invisibleInDataGrid": false,
                "invisibleLabel": false,
                "enableCustomValidation": false,
                "customValidationRule": "",
                "customValidationErrorMessage": "",
                "mask": "",
                "lookupOpenInModalDisabled": false,
                "propName": "lastEditedBy"
              },
              {
                "type": "datepicker",
                "name": "control_d014eb40-2cd9-11ec-a2f7-879f75befbaf",
                "fieldName": "control_d014eb40-2cd9-11ec-a2f7-879f75befbaf",
                "label": "Last edit date",
                "order": 0,
                "defaultValue": "",
                "value": "",
                "className": "col-md-6",
                "readonly": true,
                "readonlyCondition": "",
                "placeholder": "",
                "required": false,
                "requiredCondition": "",
                "isMultiLine": false,
                "isInteger": false,
                "decimalPlace": 0,
                "isTodayValue": false,
                "isTodayValueCreated": true,
                "dateFormat": "mm/dd/yy hh:mm p",
                "isCurrentUser": false,
                "isCurrentUserOwner": true,
                "isNowTimeValue": false,
                "timeFormat": "HH:mm",
                "isMultiple": false,
                "isAjax": false,
                "dataOptions": [],
                "ajaxDataUrl": "",
                "isChecked": false,
                "vif": "",
                "customCode": "",
                "invisible": true,
                "invisibleCondition": "",
                "invisibleInDataGrid": false,
                "invisibleLabel": false,
                "enableCustomValidation": false,
                "customValidationRule": "",
                "customValidationErrorMessage": "",
                "mask": "",
                "lookupOpenInModalDisabled": false,
                "propName": "lastEditDate"
              }
            ]
          }
        ]
      }
    ],
    "layout": "collapse",
    "_uniqueId": 0.1830877359650971
  },
  "source": "investorTypes",
  "storageType": "dashboard",
  "title": "Investor Types"
}