{
  "displayColumn": "name",
  "isReactive": true,
  "meta": {
    "layout": {
      "displayName": "Layout",
      "order": 1,
      "type": "select"
    },
    "name": {
      "displayName": "Name",
      "order": 0,
      "type": "string"
    }
  },
  "rowEditorFieldsForm": {
    "sections": [
      {
        "name": "section_352804",
        "label": "",
        "clientKey": "section_352804",
        "order": 0,
        "rows": [
          {
            "name": "section_352804_row_138024",
            "label": "",
            "order": 0,
            "controls": [
              {
                "type": "text",
                "name": "control_text_65347",
                "fieldName": "control_text_65347",
                "label": "Name",
                "order": 0,
                "defaultValue": "",
                "value": "",
                "className": "col-md-12",
                "readonly": true,
                "readonlyCondition": "",
                "placeholder": "",
                "labelBold": false,
                "labelItalic": false,
                "labelUnderline": false,
                "required": false,
                "requiredCondition": "",
                "isMultiLine": false,
                "isInteger": false,
                "decimalPlace": 0,
                "isTodayValue": false,
                "isTodayValueCreated": true,
                "dateFormat": "mm/dd/yy hh:mm p",
                "isCurrentUser": false,
                "isCurrentUserOwner": true,
                "isNowTimeValue": false,
                "timeFormat": "HH:mm",
                "isMultiple": false,
                "isAjax": false,
                "dataOptions": [],
                "ajaxDataUrl": "",
                "isChecked": false,
                "vif": "",
                "customCode": "",
                "invisible": false,
                "invisibleCondition": "",
                "invisibleInDataGrid": false,
                "invisibleLabel": false,
                "enableCustomValidation": false,
                "customValidationRule": "",
                "customValidationErrorMessage": "",
                "propName": "name",
                "gridId": "jobRoles"
              },
              {
                "type": "select",
                "name": "control_2e83f420-1ac2-11ec-a8d1-69a815e4059c",
                "fieldName": "control_2e83f420-1ac2-11ec-a8d1-69a815e4059c",
                "label": "Layout",
                "order": 0,
                "defaultValue": "",
                "value": "",
                "className": "col-md-6",
                "readonly": false,
                "readonlyCondition": "",
                "placeholder": "",
                "required": false,
                "requiredCondition": "",
                "isMultiLine": false,
                "isInteger": false,
                "decimalPlace": 0,
                "isTodayValue": false,
                "isTodayValueCreated": true,
                "dateFormat": "mm/dd/yy hh:mm p",
                "isCurrentUser": false,
                "isCurrentUserOwner": true,
                "isNowTimeValue": false,
                "timeFormat": "HH:mm",
                "isMultiple": false,
                "isAjax": false,
                "dataOptions": [],
                "ajaxDataUrl": "",
                "isChecked": false,
                "vif": "",
                "customCode": "",
                "invisible": false,
                "invisibleCondition": "",
                "invisibleInDataGrid": false,
                "invisibleLabel": false,
                "enableCustomValidation": false,
                "customValidationRule": "",
                "customValidationErrorMessage": "",
                "mask": "",
                "lookupOpenInModalDisabled": false,
                "propName": "layout"
              }
            ]
          }
        ],
        "labelPosition": "top",
        "isDynamic": false,
        "minInstance": 1,
        "maxInstance": 0,
        "instances": []
      },
      {
        "cleintKey": "hidden_section_d956c3f0-fe6b-11eb-8b02-1947c31ab3cb",
        "instances": [],
        "isDynamic": false,
        "label": "Hidden Section",
        "vif": "false",
        "name": "hidden_section_d956c3f0-fe6b-11eb-8b02-1947c31ab3cb",
        "order": 1,
        "rows": [
          {
            "name": "hidden_section_d956c3f0-fe6b-11eb-8b02-1947c31ab3cb_row_d956c3f1-fe6b-11eb-8b02-1947c31ab3cb",
            "controls": []
          }
        ]
      }
    ],
    "layout": "collapse",
    "_uniqueId": 0.5308645927636435
  },
  "source": "jobRoles",
  "storageType": "dashboard",
  "title": "Job Roles"
}