{
  "accountType": "CompanyUser",
  "activeCompanyName": "Huboo",
  "activeMinutesRoom": "-MjEtbIXOue_G0Ob7gS7",
  "activeUserFirstName": "Support",
  "activeUserSecondName": "True Altitude",
  "activecompanyProfile": "-MdH433LGlxAWUOZx1P1",
  "applications_lastViews": "",
  "companyDisclaimerRead": "true",
  "companyProfiles_lastViews": "adminView",
  "companyUserProfiles_lastViews": "companyUserApproval",
  "cookieConsent": "true",
  "filterCompany": "-MMzZ2krPwl50hP5t54m",
  "filterCompanyUser": "-MZMta3pwumGA07UlWEe",
  "filterMentor": "-MZSG7lgSWJYuL6D1E_3",
  "hideBack": "YES",
  "investorProfiles_lastViews": "investorApproval",
  "mentors_lastViews": "mentorApproval",
  "profileID": "-MkCt4HXbnk2U45svnTL",
  "programmePartnerProfiles_lastViews": "",
  "sessionDirection": "CompanyUser->Mentor"
}